python_wait_on/__init__.py
python_wait_on/cli.py
python_wait_on/wait_on.py
python_wait_on/resources/__init__.py
python_wait_on/resources/directory_resource.py
python_wait_on/resources/file_resource.py
python_wait_on/resources/http_resource.py
python_wait_on/resources/socket_resource.py
python_wait_on/resources/tcp_resource.py
tests/__init__.py
tests/test_resources.py
tests/test_wait_on.py
wait_on-0.1.1.dist-info/LICENSE
wait_on-0.1.1.dist-info/METADATA
wait_on-0.1.1.dist-info/WHEEL
wait_on-0.1.1.dist-info/entry_points.txt
wait_on-0.1.1.dist-info/top_level.txt
wait_on-0.1.1.dist-info/RECORD
